gokinjo/__init__.py
gokinjo/api.py
gokinjo/backend_annoy.py
gokinjo/backend_base.py
gokinjo/backend_sklearn.py
gokinjo/preprocessing.py
gokinjo-0.1.0.dist-info/LICENSE
gokinjo-0.1.0.dist-info/METADATA
gokinjo-0.1.0.dist-info/WHEEL
gokinjo-0.1.0.dist-info/top_level.txt
gokinjo-0.1.0.dist-info/RECORD
