Metadata-Version: 2.1
Name: gokinjo
Version: 0.1.0
Summary: k-NN feature extraction utility
Home-page: https://github.com/momijiame/gokinjo
Author: momijiame
License: Apache License, Version 2.0
Platform: UNKNOWN
Classifier: Development Status :: 4 - Beta
Classifier: Intended Audience :: Science/Research
Classifier: Operating System :: Unix
Classifier: Programming Language :: Python
Classifier: Programming Language :: Python :: 3
Classifier: Programming Language :: Python :: 3.6
Classifier: Programming Language :: Python :: 3.7
Requires-Dist: numpy
Requires-Dist: scikit-learn
Provides-Extra: annoy
Requires-Dist: annoy ; extra == 'annoy'
Provides-Extra: develop
Requires-Dist: pytest ; extra == 'develop'
Requires-Dist: pytest-flake8 ; extra == 'develop'
Requires-Dist: pytest-cov ; extra == 'develop'
Requires-Dist: annoy ; extra == 'develop'
Requires-Dist: matplotlib ; extra == 'develop'
Provides-Extra: testing
Requires-Dist: pytest ; extra == 'testing'
Requires-Dist: pytest-flake8 ; extra == 'testing'
Requires-Dist: pytest-cov ; extra == 'testing'
Requires-Dist: annoy ; extra == 'testing'
